azdocgen/__init__.py
azdocgen/cli.py
azdocgen/conditions.py
azdocgen/generate_doc.py
azdocgen/generate_mermaid.py
azdocgen/header.py
azdocgen/jobs.py
azdocgen/parameters.py
azdocgen/resources.py
azdocgen/stages.py
azdocgen/steps.py
azdocgen/triggers.py
azdocgen/variables.py
azdocgen-0.1.10.dist-info/LICENSE
azdocgen-0.1.10.dist-info/METADATA
azdocgen-0.1.10.dist-info/WHEEL
azdocgen-0.1.10.dist-info/entry_points.txt
azdocgen-0.1.10.dist-info/RECORD
